napari_file_watcher/FileReader.py
napari_file_watcher/FileWatcher.py
napari_file_watcher/__init__.py
napari_file_watcher/main_module.py
napari_file_watcher/napari.yaml
napari_file_watcher/guitools/BetterPushButton.py
napari_file_watcher/guitools/__init__.py
napari_file_watcher/guitools/dialogtools.py
tests/__init__.py
tests/test_filewatcher.py
tests/test_script.py
napari_file_watcher-0.1.1.dist-info/LICENSE
napari_file_watcher-0.1.1.dist-info/METADATA
napari_file_watcher-0.1.1.dist-info/WHEEL
napari_file_watcher-0.1.1.dist-info/entry_points.txt
napari_file_watcher-0.1.1.dist-info/top_level.txt
napari_file_watcher-0.1.1.dist-info/RECORD
