Metadata-Version: 2.1
Name: napari-file-watcher
Version: 0.1.1
Summary: A napari plugin for file watching
Home-page: https://github.com/kasasxav/napari-file-watcher
Author: Xavier Casas Moreno
Author-email: xaviercm@kth.se
License: GPL-3.0
Project-URL: Bug Tracker, https://github.com/kasasxav/napari-file-watcher
Project-URL: Documentation, https://github.com/kasasxav/napari-file-watcher/blob/main/README.md
Project-URL: Source Code, https://github.com/kasasxav/napari-file-watcher
Project-URL: User Support, https://github.com/kasasxav/napari-file-watcher/issues
Classifier: Framework :: napari
Classifier: Programming Language :: Python :: 3
Classifier: Programming Language :: Python :: 3.8
License-File: LICENSE
Requires-Dist: napari
Requires-Dist: ome-zarr
Requires-Dist: zarr
Requires-Dist: h5py
Requires-Dist: PyQt5
Requires-Dist: qtpy
Requires-Dist: QScintilla
